CHANGELOG.rst
MANIFEST.in
README.rst
setup.py
flextls/__about__.py
flextls/__init__.py
flextls/connection.py
flextls/exception.py
flextls/field.py
flextls/helper.py
flextls.egg-info/PKG-INFO
flextls.egg-info/SOURCES.txt
flextls.egg-info/dependency_links.txt
flextls.egg-info/not-zip-safe
flextls.egg-info/requires.txt
flextls.egg-info/top_level.txt
flextls/_registry/__init__.py
flextls/_registry/data.py
flextls/protocol/__init__.py
flextls/protocol/alert.py
flextls/protocol/change_cipher_spec.py
flextls/protocol/heartbeat.py
flextls/protocol/record.py
flextls/protocol/handshake/__init__.py
flextls/protocol/handshake/extension.py
tests/__init__.py
tests/test_alert.py
tests/test_dtls_1_0.py
tests/test_extension.py
tests/test_field.py
tests/test_heartbeat.py
tests/test_ssl_2_0.py
tests/test_ssl_3_0.py