Metadata-Version: 1.1
Name: flextls
Version: 0.3
Summary: Pure Python SSL and TLS library
Home-page: http://github.com/DinoTools/python-flextls
Author: PhiBo (DinoTools)
Author-email: UNKNOWN
License: LGPLv3+
Platform: UNKNOWN
Classifier: Development Status :: 3 - Alpha
Classifier: License :: OSI Approved :: GNU Lesser General Public License v3 or later (LGPLv3+)
Classifier: Operating System :: OS Independent
Classifier: Programming Language :: Python
Classifier: Programming Language :: Python :: 2.6
Classifier: Programming Language :: Python :: 2.7
Classifier: Programming Language :: Python :: 3
Classifier: Programming Language :: Python :: 3.2
Classifier: Programming Language :: Python :: 3.3
Classifier: Programming Language :: Python :: 3.4
